lasssi/__init__.py
lasssi/main.py
lasssi/assets/lasssi_audio.mp3
lasssi/assets/lasssi_video.mp4
lasssi-0.1.dist-info/LICENSE
lasssi-0.1.dist-info/METADATA
lasssi-0.1.dist-info/WHEEL
lasssi-0.1.dist-info/entry_points.txt
lasssi-0.1.dist-info/top_level.txt
lasssi-0.1.dist-info/RECORD
