Metadata-Version: 2.1
Name: lasssi
Version: 0.1
Summary: nhi bataunga
Author: nhi bataunga
License-File: LICENSE
Requires-Dist: pygame
Requires-Dist: colorama
